icrp107_database/__init__.py
icrp107_database/icrp107-schema.json
icrp107_database/utility.py
icrp107_database/icrp107/Ac-223.json
icrp107_database/icrp107/Ac-224.json
icrp107_database/icrp107/Ac-225.json
icrp107_database/icrp107/Ac-226.json
icrp107_database/icrp107/Ac-227.json
icrp107_database/icrp107/Ac-228.json
icrp107_database/icrp107/Ac-230.json
icrp107_database/icrp107/Ac-231.json
icrp107_database/icrp107/Ac-232.json
icrp107_database/icrp107/Ac-233.json
icrp107_database/icrp107/Ag-100m.json
icrp107_database/icrp107/Ag-101.json
icrp107_database/icrp107/Ag-102.json
icrp107_database/icrp107/Ag-102m.json
icrp107_database/icrp107/Ag-103.json
icrp107_database/icrp107/Ag-104.json
icrp107_database/icrp107/Ag-104m.json
icrp107_database/icrp107/Ag-105.json
icrp107_database/icrp107/Ag-105m.json
icrp107_database/icrp107/Ag-106.json
icrp107_database/icrp107/Ag-106m.json
icrp107_database/icrp107/Ag-108.json
icrp107_database/icrp107/Ag-108m.json
icrp107_database/icrp107/Ag-109m.json
icrp107_database/icrp107/Ag-110.json
icrp107_database/icrp107/Ag-110m.json
icrp107_database/icrp107/Ag-111.json
icrp107_database/icrp107/Ag-111m.json
icrp107_database/icrp107/Ag-112.json
icrp107_database/icrp107/Ag-113.json
icrp107_database/icrp107/Ag-113m.json
icrp107_database/icrp107/Ag-114.json
icrp107_database/icrp107/Ag-115.json
icrp107_database/icrp107/Ag-116.json
icrp107_database/icrp107/Ag-117.json
icrp107_database/icrp107/Ag-99.json
icrp107_database/icrp107/Al-26.json
icrp107_database/icrp107/Al-28.json
icrp107_database/icrp107/Al-29.json
icrp107_database/icrp107/Am-237.json
icrp107_database/icrp107/Am-238.json
icrp107_database/icrp107/Am-239.json
icrp107_database/icrp107/Am-240.json
icrp107_database/icrp107/Am-241.json
icrp107_database/icrp107/Am-242.json
icrp107_database/icrp107/Am-242m.json
icrp107_database/icrp107/Am-243.json
icrp107_database/icrp107/Am-244.json
icrp107_database/icrp107/Am-244m.json
icrp107_database/icrp107/Am-245.json
icrp107_database/icrp107/Am-246.json
icrp107_database-0.0.3.dist-info/licenses/LICENSE.md
icrp107_database-0.0.3.dist-info/METADATA
icrp107_database-0.0.3.dist-info/WHEEL
icrp107_database-0.0.3.dist-info/top_level.txt
icrp107_database-0.0.3.dist-info/RECORD
