Metadata-Version: 2.4
Name: icrp107-database
Version: 0.0.3
Summary: Data for radionuclide spectra
Author-email: Opengate collaboration <david.sarrut@creatis.insa-lyon.fr>
License:                    GNU LESSER GENERAL PUBLIC LICENSE
Classifier: Programming Language :: Python
Classifier: Programming Language :: Python :: 3.9
Classifier: Programming Language :: Python :: 3.10
Classifier: Programming Language :: Python :: 3.11
Classifier: Programming Language :: Python :: 3.12
Classifier: Programming Language :: Python :: Implementation :: PyPy
Classifier: Operating System :: OS Independent
Requires-Python: >=3.9
License-File: LICENSE.md
Dynamic: license-file
